edge_detector/rtl/top.v
module edge_detector (
	input wire clk,
	input wire rst_n,
	input wire sign_in,
	output reg pulse_out_p,
	output reg pulse_out_n
);

reg sign_in_prev;

always @(posedge clk or rst_n) begin
	if(!rst_n) begin
		sign_in_prev <= 0;
		pulse_out_p <= 0;
		pulse_out_n <= 0;
	end else begin
		pulse_out_p <= sign_in & ~sign_in_prev;
		pulse_out_n <= ~sign_in & sign_in_prev;
		sign_in_prev <= sign_in;
	end
end
endmodule

edge_detector/tb/test_bench.v
`timescale 1ns/1ps
module test_bench;
	reg clk;
	reg rst_n;
	reg sign_in;
	wire pulse_out_p;
	wire pulse_out_n;

	reg exp_pulse_out_p;
	reg exp_pulse_out_n;

	edge_detector dut(
		.clk(clk),
		.rst_n(rst_n),
		.sign_in(sign_in),
		.pulse_out_p(pulse_out_p),
		.pulse_out_n(pulse_out_n)
	);

	initial begin
		clk = 0;
		forever #5 clk = ~clk;
	end

	task verify;
		input exp_pulse_out_p;
		input pulse_out_p;
		input exp_pulse_out_n;
		input pulse_out_n;
		begin
			if((exp_pulse_out_p == pulse_out_p)&&(exp_pulse_out_n == pulse_out_n)) begin
				$display("-----------------------------------------------------------------------------------------------------------------");
				$display("PASSED: Expected pulse_out_p: %b, Got pulse_out_p: %b, Expected pulse_out_n: %b, pulse_out_n: %b", exp_pulse_out_p, pulse_out_p, exp_pulse_out_n, pulse_out_n);
				$display("-----------------------------------------------------------------------------------------------------------------");
			end else begin
				$display("-----------------------------------------------------------------------------------------------------------------");
				$display("PASSED: Expected pulse_out_p: %b, Got pulse_out_p: %b, Expected pulse_out_n: %b, pulse_out_n: %b", exp_pulse_out_p, pulse_out_p, exp_pulse_out_n, pulse_out_n);
				$display("-----------------------------------------------------------------------------------------------------------------");
			end
		end
	endtask

	initial begin
		$dumpfile("test_bench.vcd");
		$dumpvars(0, test_bench);

		$display("-------------------------------------------------------------------------------------------------------------------");
		$display("------------------------------------TESTBENCH FOR EDGE DETECTOR ---------------------------------------------------");
		$display("-------------------------------------------------------------------------------------------------------------------");

		rst_n = 0;
		sign_in = 0;
		exp_pulse_out_p = 0;
		exp_pulse_out_n = 0;
		#1;
		verify(exp_pulse_out_p, pulse_out_p, exp_pulse_out_n, pulse_out_n);

		#10;
		rst_n = 1;

		#10;
		sign_in = 1;
		exp_pulse_out_p = 1;
		exp_pulse_out_n = 0;
		#1;
		verify(exp_pulse_out_p, pulse_out_p, exp_pulse_out_n, pulse_out_n);

		#10;
		sign_in = 0;
		exp_pulse_out_p = 0;
		exp_pulse_out_n = 1;
		#1;
		verify(exp_pulse_out_p, pulse_out_p, exp_pulse_out_n, pulse_out_n);

		#10;
		sign_in = 0;
		exp_pulse_out_p = 0;
		exp_pulse_out_n = 0;
		#1;
		verify(exp_pulse_out_p, pulse_out_p, exp_pulse_out_n, pulse_out_n);

		#10;
		sign_in = 1;
		exp_pulse_out_p = 1;
		exp_pulse_out_n = 0;
		#1;
		verify(exp_pulse_out_p, pulse_out_p, exp_pulse_out_n, pulse_out_n);

		#10;
		sign_in = 1;
		exp_pulse_out_p = 0;
		exp_pulse_out_n = 0;
		#1;
		verify(exp_pulse_out_p, pulse_out_p, exp_pulse_out_n, pulse_out_n);

		#10;
		sign_in = 0;
		exp_pulse_out_p = 0;
		exp_pulse_out_n = 1;
		#1;
		verify(exp_pulse_out_p, pulse_out_p, exp_pulse_out_n, pulse_out_n);

		#100;
		$finish;
	end
endmodule

edge_detector/sim/test_bench.vcd
$date
	Thu Jan  2 23:13:57 2025
$end
$version
	Icarus Verilog
$end
$timescale
	1ps
$end
$scope module test_bench $end
$var wire 1 ! pulse_out_p $end
$var wire 1 " pulse_out_n $end
$var reg 1 # clk $end
$var reg 1 $ exp_pulse_out_n $end
$var reg 1 % exp_pulse_out_p $end
$var reg 1 & rst_n $end
$var reg 1 ' sign_in $end
$scope module dut $end
$var wire 1 # clk $end
$var wire 1 & rst_n $end
$var wire 1 ' sign_in $end
$var reg 1 " pulse_out_n $end
$var reg 1 ! pulse_out_p $end
$var reg 1 ( sign_in_prev $end
$upscope $end
$scope task verify $end
$var reg 1 ) exp_pulse_out_n $end
$var reg 1 * exp_pulse_out_p $end
$var reg 1 + pulse_out_n $end
$var reg 1 , pulse_out_p $end
$upscope $end
$upscope $end
$enddefinitions $end
$comment Show the parameter values. $end
$dumpall
$end
#0
$dumpvars
x,
x+
x*
x)
0(
0'
0&
0%
0$
0#
0"
0!
$end
#1000
0+
0)
0,
0*
#5000
1#
#10000
0#
#11000
1&
#15000
1#
#20000
0#
#21000
1%
1'
#22000
1*
#25000
1(
1!
1#
#30000
0#
#32000
1$
0%
0'
#33000
1)
1,
0*
#35000
0(
1"
0!
1#
#40000
0#
#43000
0$
#44000
1+
0)
0,
#45000
0"
1#
#50000
0#
#54000
1%
1'
#55000
1(
1!
0+
1*
1#
#60000
0#
#65000
0!
1#
0%
#66000
0*
#70000
0#
#75000
1#
#76000
1$
0'
#77000
1)
#80000
0#
#85000
0(
1"
1#
#90000
0#
#95000
0"
1#
